janus/__init__.py
janus/analysis/__init__.py
janus/analysis/pii_scanner.py
janus/attack/__init__.py
janus/attack/bfla.py
janus/attack/graphql.py
janus/attack/race_condition.py
janus/attack/ssrf.py
janus/core/__init__.py
janus/core/database.py
janus/core/engine.py
janus/core/hivemind.py
janus/core/http_client.py
janus/core/jwt_attacks.py
janus/core/mass_assignment.py
janus/core/notifications.py
janus/core/proxy.py
janus/core/reporting.py
janus/core/smart_diff.py
janus/core/stealth.py
janus/interface/__init__.py
janus/interface/cli.py
janus/interface/web/__init__.py
janus/interface/web/server.py
janus/recon/__init__.py
janus/recon/cve_lookup.py
janus/recon/shadow.py
janus/reporting/__init__.py
janus/reporting/sarif.py
janus_security-0.1.3.dist-info/METADATA
janus_security-0.1.3.dist-info/WHEEL
janus_security-0.1.3.dist-info/entry_points.txt
janus_security-0.1.3.dist-info/licenses/LICENSE
janus_security-0.1.3.dist-info/RECORD
