Metadata-Version: 2.4
Name: janus-security
Version: 0.1.3
Summary: Enterprise-grade BOLA and API Vulnerability Scanner
Project-URL: Homepage, https://github.com/ksanjeev284/janus
Project-URL: Issues, https://github.com/ksanjeev284/janus/issues
Author-email: Sanjeev Kumar <ksanjeev284@gmail.com>
License-File: LICENSE
Classifier: Development Status :: 4 - Beta
Classifier: Intended Audience :: Developers
Classifier: Intended Audience :: System Administrators
Classifier: License :: OSI Approved :: MIT License
Classifier: Programming Language :: Python :: 3.10
Classifier: Programming Language :: Python :: 3.11
Classifier: Programming Language :: Python :: 3.12
Classifier: Topic :: Security
Classifier: Topic :: Software Development :: Testing
Requires-Python: >=3.10
Requires-Dist: fake-useragent>=1.1.0
Requires-Dist: fastapi>=0.100.0
Requires-Dist: python-multipart>=0.0.6
Requires-Dist: redis>=5.0.0
Requires-Dist: requests>=2.31.0
Requires-Dist: rich>=13.0.0
Requires-Dist: typer>=0.9.0
Requires-Dist: uvicorn>=0.23.0
